mccrapipy/__init__.py
mccrapipy/items.py
mccrapipy-0.0.9.dist-info/METADATA
mccrapipy-0.0.9.dist-info/WHEEL
mccrapipy-0.0.9.dist-info/top_level.txt
mccrapipy-0.0.9.dist-info/RECORD
